LICENSE
README.md
setup.py
aaspip/__init__.py
aaspip.egg-info/PKG-INFO
aaspip.egg-info/SOURCES.txt
aaspip.egg-info/dependency_links.txt
aaspip.egg-info/not-zip-safe
aaspip.egg-info/requires.txt
aaspip.egg-info/top_level.txt
aaspip/drr/__init__.py
aaspip/drr/bins.py
aaspip/drr/drr3d.py
aaspip/drr/drr3d_win.py
aaspip/drr/drr5d.py
aaspip/drr/genmask.py
aaspip/drr/localfun.py
aaspip/drr/snr.py
aaspip/drr/utils.py
aaspip/drr/window.py
aaspip/ekfmm/__init__.py
aaspip/ekfmm/fmm.py
aaspip/ekfmm/fmmvti.py
aaspip/ekfmm/stream.py
aaspip/ekfmm/test.py
aaspip/ekfmm/tomo.py
aaspip/ekfmm/src/eikonal.c
aaspip/ekfmm/src/eikonalvti.c
aaspip/npre/__init__.py
aaspip/npre/npre3d.py
aaspip/npre/tf.py
aaspip/npre/src/npre3d.c
aaspip/npre/src/npre_alloc.c
aaspip/npre/src/npre_alloc.h
aaspip/npre/src/npre_cdivn.c
aaspip/npre/src/npre_cdivn.h
aaspip/npre/src/npre_conjgrad.c
aaspip/npre/src/npre_conjgrad.h
aaspip/npre/src/npre_decart.c
aaspip/npre/src/npre_decart.h
aaspip/npre/src/npre_dtype.h
aaspip/npre/src/npre_fft1.c
aaspip/npre/src/npre_fxynpre.c
aaspip/npre/src/npre_fxynpre.h
aaspip/npre/src/npre_kissfft.c
aaspip/npre/src/npre_kissfft.h
aaspip/npre/src/npre_komplex.c
aaspip/npre/src/npre_komplex.h
aaspip/npre/src/npre_memcpy.c
aaspip/npre/src/npre_memcpy.h
aaspip/npre/src/npre_ntriangle.c
aaspip/npre/src/npre_ntriangle.h
aaspip/npre/src/npre_ntrianglen.c
aaspip/npre/src/npre_ntrianglen.h
aaspip/npre/src/npre_triangle.c
aaspip/npre/src/npre_triangle.h
aaspip/npre/src/npre_trianglen.c
aaspip/npre/src/npre_trianglen.h
aaspip/npre/src/npre_win.c
aaspip/npre/src/npre_win.h
aaspip/npre/src/tf.c
aaspip/ntfa/__init__.py
aaspip/ntfa/ntfa.py
aaspip/ntfa/readwrite.py
aaspip/ntfa/src/main.c
aaspip/ntfa/src/ntfa_alloc.c
aaspip/ntfa/src/ntfa_alloc.h
aaspip/ntfa/src/ntfa_blas.c
aaspip/ntfa/src/ntfa_blas.h
aaspip/ntfa/src/ntfa_conjgrad.c
aaspip/ntfa/src/ntfa_conjgrad.h
aaspip/ntfa/src/ntfa_decart.c
aaspip/ntfa/src/ntfa_decart.h
aaspip/ntfa/src/ntfa_divnnsc.c
aaspip/ntfa/src/ntfa_divnnsc.h
aaspip/ntfa/src/ntfa_ntriangle.c
aaspip/ntfa/src/ntfa_ntriangle.h
aaspip/ntfa/src/ntfa_ntrianglen.c
aaspip/ntfa/src/ntfa_ntrianglen.h
aaspip/ntfa/src/ntfa_triangle.c
