Metadata-Version: 2.1
Name: aaspip
Version: 0.0.0.1
Summary: AASPIP: Advanced Array Seismic Data Processing and Imaging Platform
Home-page: https://github.com/aaspip/aaspip
Author: aaspip developing team
Author-email: chenyk2016@gmail.com
License: MIT License
Keywords: seismology,earthquake seismology,exploration seismology,array seismology,denoising,science,engineering,structure,local slope,filtering
Classifier: Development Status :: 4 - Beta
Classifier: Intended Audience :: Developers
Classifier: Intended Audience :: Science/Research
Classifier: Operating System :: Unix
Classifier: Operating System :: POSIX
Classifier: Operating System :: Microsoft :: Windows
Classifier: Programming Language :: Python
Classifier: Programming Language :: Python :: 3.8
Classifier: Programming Language :: Python :: Implementation :: CPython
Classifier: Topic :: Scientific/Engineering
Classifier: Topic :: Scientific/Engineering :: Physics
License-File: LICENSE
Requires-Dist: numpy
Requires-Dist: scipy
Requires-Dist: matplotlib
Provides-Extra: docs
Requires-Dist: sphinx; extra == "docs"
Requires-Dist: ipython; extra == "docs"
Requires-Dist: runipy; extra == "docs"
